target_sdk/__init__.py
target_sdk/hello.py
target_sdk-0.0.1a0.dist-info/WHEEL
target_sdk-0.0.1a0.dist-info/METADATA
target_sdk-0.0.1a0.dist-info/RECORD
