Metadata-Version: 2.1
Name: target-sdk
Version: 0.0.1a0
Summary: SDK under development
License: Apache 2.0
Author: AJ Steers
Author-email: aj@meltano.com
Requires-Python: >=3.8,<4.0
Classifier: License :: Other/Proprietary License
Classifier: Programming Language :: Python :: 3
Classifier: Programming Language :: Python :: 3.8
Classifier: Programming Language :: Python :: 3.9
